{"cameraMode":{"drawMode":0,"name":"Shaded","section":"Shading Mode"},"sceneLighting":true,"audioPlay":false,"sceneViewState":{"m_AlwaysRefresh":false,"showFog":true,"showSkybox":true,"showFlares":true,"showImageEffects":true,"showParticleSystems":true,"showVisualEffectGraphs":true,"m_FxEnabled":true},"in2DMode":false,"pivot":{"x":907.15234375,"y":1324.802001953125,"z":589.52001953125},"rotation":{"x":-0.048287760466337207,"y":0.0009071269887499511,"z":-0.00006296807987382635,"w":-0.9987578988075256},"size":1417.6689453125,"orthographic":false}